logEZ/__init__.py
logEZ/formatters.py
logEZ/handlers.py
logEZ/mylogger.py
logEZ-0.1.0.dist-info/LICENSE
logEZ-0.1.0.dist-info/METADATA
logEZ-0.1.0.dist-info/WHEEL
logEZ-0.1.0.dist-info/top_level.txt
logEZ-0.1.0.dist-info/RECORD
