Metadata-Version: 2.1
Name: logEZ
Version: 0.1.0
Summary: A simple(r) logger for Python
Home-page: https://github.com/KunalGehlot/logEZ
Author: Zackcodes.ai
Author-email: gehlotkunal@outlook.com
License: MIT
Keywords: logging
Classifier: Development Status :: 3 - Alpha
Classifier: Intended Audience :: Developers
Classifier: License :: OSI Approved :: MIT License
Classifier: Programming Language :: Python :: 3
Classifier: Programming Language :: Python :: 3.8
Classifier: Programming Language :: Python :: 3.9
Classifier: Programming Language :: Python :: 3.10
Classifier: Operating System :: OS Independent
Requires-Python: >=3.8
License-File: LICENSE
